pyrack/__init__.py
pyrack/object.py
pyrack-0.0.10.dist-info/METADATA
pyrack-0.0.10.dist-info/WHEEL
pyrack-0.0.10.dist-info/top_level.txt
pyrack-0.0.10.dist-info/RECORD
